markpub_bskypost/__init__.py
markpub_bskypost/bluesky_post.py
markpub_bskypost/markpub_bskypost.py
markpub_bskypost-1.0.1.dist-info/METADATA
markpub_bskypost-1.0.1.dist-info/WHEEL
markpub_bskypost-1.0.1.dist-info/entry_points.txt
markpub_bskypost-1.0.1.dist-info/licenses/LICENSE
markpub_bskypost-1.0.1.dist-info/RECORD
