Metadata-Version: 2.4
Name: markpub_bskypost
Version: 1.0.1
Summary: Bluesky comments support for MarkPub websites
Project-URL: repository, https://github.com/band/markpub-bskypost
Author-email: "William L. Anderson" <band@acm.org>
License: MIT
License-File: LICENSE
Requires-Python: >=3.12
Requires-Dist: bs4<0.0.3,>=0.0.2
Requires-Dist: python-dotenv<2.0.0,>=1.0.1
Requires-Dist: pyyaml<7.0.0,>=6.0.2
Requires-Dist: requests<3.0.0,>=2.32.3
